slixmpp_jingle/__init__.py
slixmpp_jingle/version.py
slixmpp_jingle/xep_0166/__init__.py
slixmpp_jingle/xep_0166/jingle.py
slixmpp_jingle/xep_0166/stanza.py
slixmpp_jingle/xep_0167/__init__.py
slixmpp_jingle/xep_0167/rtp.py
slixmpp_jingle/xep_0167/stanza.py
slixmpp_jingle/xep_0176/__init__.py
slixmpp_jingle/xep_0176/stanza.py
slixmpp_jingle/xep_0176/transport.py
slixmpp_jingle/xep_0177/__init__.py
slixmpp_jingle/xep_0177/stanza.py
slixmpp_jingle/xep_0177/transport.py
slixmpp_jingle/xep_0215/__init__.py
slixmpp_jingle/xep_0215/services.py
slixmpp_jingle/xep_0215/stanza.py
slixmpp_jingle/xep_0262/__init__.py
slixmpp_jingle/xep_0262/stanza.py
slixmpp_jingle/xep_0262/zrtp.py
slixmpp_jingle/xep_0293/__init__.py
slixmpp_jingle/xep_0293/rtcpfb.py
slixmpp_jingle/xep_0293/stanza.py
slixmpp_jingle/xep_0294/__init__.py
slixmpp_jingle/xep_0294/hdrext.py
slixmpp_jingle/xep_0294/stanza.py
slixmpp_jingle/xep_0320/__init__.py
slixmpp_jingle/xep_0320/fingerprint.py
slixmpp_jingle/xep_0320/stanza.py
slixmpp_jingle/xep_0338/__init__.py
slixmpp_jingle/xep_0338/group.py
slixmpp_jingle/xep_0338/stanza.py
slixmpp_jingle/xep_0339/__init__.py
slixmpp_jingle/xep_0339/source.py
slixmpp_jingle/xep_0339/stanza.py
slixmpp_jingle-0.9.0.dist-info/METADATA
slixmpp_jingle-0.9.0.dist-info/WHEEL
slixmpp_jingle-0.9.0.dist-info/top_level.txt
slixmpp_jingle-0.9.0.dist-info/RECORD
